jaggimage_viewer/__init__.py
jaggimage_viewer/__main__.py
jaggimage_viewer/_version.py
jaggimage_viewer/jaggimage_viewer.py
jaggimage_viewer-1.1.4.dist-info/METADATA
jaggimage_viewer-1.1.4.dist-info/WHEEL
jaggimage_viewer-1.1.4.dist-info/entry_points.txt
jaggimage_viewer-1.1.4.dist-info/licenses/LICENSE
jaggimage_viewer-1.1.4.dist-info/RECORD
