Metadata-Version: 2.4
Name: jaggimage-viewer
Version: 1.1.4
Summary: A nice image viewer in the spirit of ACDSee
Project-URL: Homepage, https://github.com/clxjaguar/jaggimage-viewer
Project-URL: Issues, https://github.com/clxjaguar/jaggimage-viewer/issues
Project-URL: Documentation, https://pypi.org/project/jaggimage-viewer/
Author-email: cLx <clx.kat@gmail.com>
License-Expression: GPL-3.0-or-later
License-File: LICENSE
Keywords: ACDSee replacement,Qt,image viewer
Classifier: Development Status :: 5 - Production/Stable
Classifier: Environment :: X11 Applications :: Qt
Classifier: License :: OSI Approved :: GNU General Public License v3 (GPLv3)
Classifier: Operating System :: OS Independent
Classifier: Programming Language :: Python :: 3
Classifier: Topic :: Multimedia :: Graphics :: Viewers
Requires-Python: >=3.10
Requires-Dist: pyqt5>=5.15.11
